readmdict/__init__.py
readmdict/__main__.py
readmdict/_readmdict.py
readmdict/CY_MDict/MDict.cp39-win_amd64.pyd
readmdict/CY_MDict/MDict.pyx
readmdict/CY_MDict/setup.py
readmdict/pureSalsa20.py
readmdict/readmdict.py
readmdict/ripemd128.py
faster_readmdict-0.1.4.dist-info/entry_points.txt
faster_readmdict-0.1.4.dist-info/METADATA
faster_readmdict-0.1.4.dist-info/WHEEL
faster_readmdict-0.1.4.dist-info/RECORD
