Metadata-Version: 2.1
Name: faster-readmdict
Version: 0.1.4
Summary: readmdict (simple repacking of readmdict in mdict-analysis)
Home-page: https://github.com/ovo-Tim/faster-readmdict
License: MIT
Author: ovo-Tim
Requires-Python: >=3.6.1,<4.0.0
Classifier: License :: OSI Approved :: MIT License
Classifier: Programming Language :: Python :: 3
Classifier: Programming Language :: Python :: 3.7
Classifier: Programming Language :: Python :: 3.8
Classifier: Programming Language :: Python :: 3.9
Classifier: Programming Language :: Python :: 3.10
Classifier: Programming Language :: Python :: 3.11
Classifier: Programming Language :: Python :: 3.12
Project-URL: Repository, https://github.com/ovo-Tim/faster-readmdict
